[
  {
    "bookSourceGroup": "",
    "bookSourceName": "月朗星稀",
    "bookSourceType": 0,
    "bookSourceUrl": "https://www.aaccnn.com/",
    "customOrder": 526,
    "enabled": true,
    "enabledCookieJar": false,
    "enabledExplore": true,
    "exploreUrl": "[\n{\"title\":\"分类\",\"url\":\"\",\"style\":{\"layout_flexBasisPercent\":1,\"layout_flexGrow\":1}},\n{\"title\":\"都市激情\",\"url\":\"/category/3/{{page-1}}\",\"style\":{\"layout_flexBasisPercent\":0.25,\"layout_flexGrow\":1}},\n{\"title\":\"家庭乱伦\",\"url\":\"/category/2/{{page-1}}\",\"style\":{\"layout_flexBasisPercent\":0.25,\"layout_flexGrow\":1}},\n{\"title\":\"校园春色\",\"url\":\"/category/1/{{page-1}}\",\"style\":{\"layout_flexBasisPercent\":0.25,\"layout_flexGrow\":1}},\n{\"title\":\"东方玄幻\",\"url\":\"/category/7/{{page-1}}\",\"style\":{\"layout_flexBasisPercent\":0.25,\"layout_flexGrow\":1}},\n{\"title\":\"穿越重生\",\"url\":\"/category/6/{{page-1}}\",\"style\":{\"layout_flexBasisPercent\":0.25,\"layout_flexGrow\":1}},\n{\"title\":\"同人改编\",\"url\":\"/category/4/{{page-1}}\",\"style\":{\"layout_flexBasisPercent\":0.25,\"layout_flexGrow\":1}},\n{\"title\":\"系统异能\",\"url\":\"/category/5/{{page-1}}\",\"style\":{\"layout_flexBasisPercent\":0.25,\"layout_flexGrow\":1}},\n{\"title\":\"历史架空\",\"url\":\"/category/13/{{page-1}}\",\"style\":{\"layout_flexBasisPercent\":0.25,\"layout_flexGrow\":1}},\n{\"title\":\"经典武侠\",\"url\":\"/category/12/{{page-1}}\",\"style\":{\"layout_flexBasisPercent\":0.25,\"layout_flexGrow\":1}},\n{\"title\":\"乡村爱情\",\"url\":\"/category/9/{{page-1}}\",\"style\":{\"layout_flexBasisPercent\":0.25,\"layout_flexGrow\":1}},\n{\"title\":\"科学幻想\",\"url\":\"/category/10/{{page-1}}\",\"style\":{\"layout_flexBasisPercent\":0.25,\"layout_flexGrow\":1}},\n{\"title\":\"娱乐明星\",\"url\":\"/category/11/{{page-1}}\",\"style\":{\"layout_flexBasisPercent\":0.25,\"layout_flexGrow\":1}},\n{\"title\":\"标签\",\"url\":\"\",\"style\":{\"layout_flexBasisPercent\":1,\"layout_flexGrow\":1}},\n{\"title\":\"人妻\",\"url\":\"/tag/9/{{page-1}}\",\"style\":{\"layout_flexBasisPercent\":0.25,\"layout_flexGrow\":1}},\n{\"title\":\"后宫\",\"url\":\"/tag/14/{{page-1}}\",\"style\":{\"layout_flexBasisPercent\":0.25,\"layout_flexGrow\":1}},\n{\"title\":\"熟女\",\"url\":\"/tag/6/{{page-1}}\",\"style\":{\"layout_flexBasisPercent\":0.25,\"layout_flexGrow\":1}},\n{\"title\":\"爽文\",\"url\":\"/tag/15/{{page-1}}\",\"style\":{\"layout_flexBasisPercent\":0.25,\"layout_flexGrow\":1}},\n{\"title\":\"调教\",\"url\":\"/tag/7/{{page-1}}\",\"style\":{\"layout_flexBasisPercent\":0.25,\"layout_flexGrow\":1}},\n{\"title\":\"NTR\",\"url\":\"/tag/56/{{page-1}}\",\"style\":{\"layout_flexBasisPercent\":0.25,\"layout_flexGrow\":1}},\n{\"title\":\"猎艳\",\"url\":\"/tag/17/{{page-1}}\",\"style\":{\"layout_flexBasisPercent\":0.25,\"layout_flexGrow\":1}},\n{\"title\":\"淫堕\",\"url\":\"/tag/8/{{page-1}}\",\"style\":{\"layout_flexBasisPercent\":0.25,\"layout_flexGrow\":1}},\n{\"title\":\"剧情\",\"url\":\"/tag/2/{{page-1}}\",\"style\":{\"layout_flexBasisPercent\":0.25,\"layout_flexGrow\":1}},\n{\"title\":\"母子\",\"url\":\"/tag/24/{{page-1}}\",\"style\":{\"layout_flexBasisPercent\":0.25,\"layout_flexGrow\":1}},\n{\"title\":\"性奴\",\"url\":\"/tag/29/{{page-1}}\",\"style\":{\"layout_flexBasisPercent\":0.25,\"layout_flexGrow\":1}},\n{\"title\":\"凌辱\",\"url\":\"/tag/58/{{page-1}}\",\"style\":{\"layout_flexBasisPercent\":0.25,\"layout_flexGrow\":1}},\n{\"title\":\"排行\",\"url\":\"\",\"style\":{\"layout_flexBasisPercent\":1,\"layout_flexGrow\":1}},\n{\"title\":\"人气排行\",\"url\":\"/top/hot/{{page==1?'':'index_'+page+'.html'}}\",\"style\":{\"layout_flexBasisPercent\":0.25,\"layout_flexGrow\":1}},\n{\"title\":\"收藏排行\",\"url\":\"/top/collect/{{page==1?'':'index_'+page+'.html'}}\",\"style\":{\"layout_flexBasisPercent\":0.25,\"layout_flexGrow\":1}},\n{\"title\":\"热门全本\",\"url\":\"/top/wanben/{{page==1?'':'index_'+page+'.html'}}\",\"style\":{\"layout_flexBasisPercent\":0.25,\"layout_flexGrow\":1}},\n{\"title\":\"肉量排行\",\"url\":\"/top/pornrate/{{page==1?'':'index_'+page+'.html'}}\",\"style\":{\"layout_flexBasisPercent\":0.25,\"layout_flexGrow\":1}},\n{\"title\":\"评分排行\",\"url\":\"/top/score/{{page==1?'':'index_'+page+'.html'}}\",\"style\":{\"layout_flexBasisPercent\":0.25,\"layout_flexGrow\":1}},\n{\"title\":\"最新小说\",\"url\":\"/top/new/{{page==1?'':'index_'+page+'.html'}}\",\"style\":{\"layout_flexBasisPercent\":0.25,\"layout_flexGrow\":1}},\n]",
    "lastUpdateTime": 1727650566197,
    "respondTime": 180000,
    "ruleBookInfo": {
      "author": ".authors@dd@text",
      "intro": ".book-desc@textNodes",
      "kind": ".tag@a@text",
      "lastChapter": ".new@dd@text",
      "name": ".txt@h1@text",
      "wordCount": ".wordcount@dd@text"
    },
    "ruleContent": {
      "content": "#content@p@textNodes"
    },
    "ruleExplore": {},
    "ruleSearch": {
      "author": "span@text",
      "bookList": ".book-like@a",
      "bookUrl": "a.0@href",
      "coverUrl": "img@src",
      "name": "h4@text"
    },
    "ruleToc": {
      "chapterList": ".book-chapter@a",
      "chapterName": "text",
      "chapterUrl": "href"
    },
    "searchUrl": "/e/search/,{\n  \"body\": \"keyboard={{key}}\",\n  \"method\": \"POST\"\n}",
    "weight": 0
  }
]